README
setup.py
rhsm.egg-info/PKG-INFO
rhsm.egg-info/SOURCES.txt
rhsm.egg-info/dependency_links.txt
rhsm.egg-info/requires.txt
rhsm.egg-info/top_level.txt
src/certificate.c
src/rhsm/__init__.py
src/rhsm/bitstream.py
src/rhsm/certificate.py
src/rhsm/certificate2.py
src/rhsm/config.py
src/rhsm/connection.py
src/rhsm/https.py
src/rhsm/huffman.py
src/rhsm/m2cryptohttp.py
src/rhsm/m2cryptossl.py
src/rhsm/ourjson.py
src/rhsm/pathtree.py
src/rhsm/profile.py
src/rhsm/utils.py
src/rhsm/version.py