Metadata-Version: 1.1
Name: rhsm
Version: 1.19.2
Summary: A Python library to communicate with a Red Hat Unified Entitlement Platform
Home-page: http://fedorahosted.org/candlepin
Author: Devan Goodwin
Author-email: dgoodwin@redhat.com
License: GPLv2
Platform: UNKNOWN
Classifier: License :: OSI Approved :: GNU General Public License (GPL)
Classifier: Intended Audience :: Developers
Classifier: Intended Audience :: Information Technology
Classifier: Programming Language :: Python
